xbwt/__init__.py
xbwt/xbwt.py
xbwt-0.0.7.dist-info/LICENSE.txt
xbwt-0.0.7.dist-info/METADATA
xbwt-0.0.7.dist-info/WHEEL
xbwt-0.0.7.dist-info/top_level.txt
xbwt-0.0.7.dist-info/RECORD
