Metadata-Version: 2.1
Name: xbwt
Version: 0.0.7
Summary: Construction of the xbw transform
Home-page: https://github.com/dolce95/xbw-transform
Author: Danilo Giovanni Dolce
Author-email: <dolcedanilo1995@gmail.com>
License: UNKNOWN
Keywords: python,xbwt,compression and indexing of labeled trees
Platform: UNKNOWN
Classifier: Development Status :: 1 - Planning
Classifier: Intended Audience :: Developers
Classifier: Programming Language :: Python :: 3
Classifier: Operating System :: Unix
Classifier: Operating System :: MacOS :: MacOS X
Classifier: Operating System :: Microsoft :: Windows
License-File: LICENSE.txt
Requires-Dist: numpy
